floquettb/__init__.py
floquettb/floquettb.py
floquettb-0.1.0.dist-info/licenses/LICENSE
floquettb-0.1.0.dist-info/METADATA
floquettb-0.1.0.dist-info/WHEEL
floquettb-0.1.0.dist-info/top_level.txt
floquettb-0.1.0.dist-info/RECORD
