Metadata-Version: 2.4
Name: floquettb
Version: 0.1.0
Summary: A Python package for Floquet engineering of tight-binding models
Home-page: https://github.com/yourusername/floquettb
Author: Your Name
Author-email: Dinghui Wang <wangdh@cumt.edu.cn>
License: MIT
Project-URL: Homepage, https://github.com/yourusername/floquettb
Project-URL: Documentation, https://github.com/yourusername/floquettb#readme
Project-URL: Repository, https://github.com/yourusername/floquettb
Project-URL: Issues, https://github.com/yourusername/floquettb/issues
Keywords: floquet,tight-binding,topology,condensed-matter,physics
Classifier: Development Status :: 3 - Alpha
Classifier: Intended Audience :: Science/Research
Classifier: Topic :: Scientific/Engineering :: Physics
Classifier: License :: OSI Approved :: MIT License
Classifier: Programming Language :: Python :: 3
Classifier: Programming Language :: Python :: 3.7
Classifier: Programming Language :: Python :: 3.8
Classifier: Programming Language :: Python :: 3.9
Classifier: Programming Language :: Python :: 3.10
Classifier: Programming Language :: Python :: 3.11
Classifier: Programming Language :: Python :: 3.12
Classifier: Programming Language :: Python :: 3.13
Requires-Python: >=3.7
License-File: LICENSE
Requires-Dist: numpy>=1.19.0
Requires-Dist: scipy>=1.5.0
Requires-Dist: matplotlib>=3.3.0
Provides-Extra: dev
Requires-Dist: pytest>=6.0; extra == "dev"
Requires-Dist: pytest-cov>=2.0; extra == "dev"
Requires-Dist: black>=21.0; extra == "dev"
Requires-Dist: flake8>=3.8; extra == "dev"
Dynamic: author
Dynamic: home-page
Dynamic: license-file
Dynamic: requires-python
